py_module_info/__init__.py
py_module_info/_core.py
py_module_info/main.py
test/__init__.py
test/test_class_info.py
test/test_function_info.py
test/test_import_info.py
test/test_main.py
py_module_info-0.1.0.dist-info/LICENSE
py_module_info-0.1.0.dist-info/METADATA
py_module_info-0.1.0.dist-info/WHEEL
py_module_info-0.1.0.dist-info/top_level.txt
py_module_info-0.1.0.dist-info/RECORD
